LICENSE
README.md
setup.cfg
setup.py
flair/__init__.py
flair/flair_helper.py
flair/resource_types.py
flair/hvac_units/__init__.py
flair/hvac_units/hvac_unit.py
flair/pucks/__init__.py
flair/pucks/puck.py
flair/rooms/__init__.py
flair/rooms/room.py
flair/structures/__init__.py
flair/structures/structure.py
flair/vents/__init__.py
flair/vents/vent.py
hass_flair_helper.egg-info/PKG-INFO
hass_flair_helper.egg-info/SOURCES.txt
hass_flair_helper.egg-info/dependency_links.txt
hass_flair_helper.egg-info/requires.txt
hass_flair_helper.egg-info/top_level.txt